[
    {
        "name": "Fruits",
        "bgImage": "",
        "categoryId": "wholefoods"
    },
    {
        "name": "Vegetables",
        "bgImage": "",
        "categoryId": "wholefoods"
    },
    {
        "name": "Meat",
        "bgImage": "",
        "categoryId": "wholefoods"
    },
    {
        "name": "Sea Food",
        "bgImage": "",
        "categoryId": "wholefoods"
    },
    {
        "name": "Bathroom & Kitchen",
        "bgImage": "",
        "categoryId": "wholefoods"
    },
    {
        "name": "Personal Care",
        "bgImage": "",
        "categoryId": "wholefoods"
    },
    {
        "name": "Dairy, Eggs & Cheese",
        "bgImage": "",
        "categoryId": "wholefoods"
    }
]